irisml/tasks/create_ultralytics_train_transform.py
irisml/tasks/create_ultralytics_val_transform.py
irisml/tasks/create_ultralytics_yolov9_detection_model.py
irisml_tasks_ultralytics-0.0.3.dist-info/LICENSE
irisml_tasks_ultralytics-0.0.3.dist-info/METADATA
irisml_tasks_ultralytics-0.0.3.dist-info/WHEEL
irisml_tasks_ultralytics-0.0.3.dist-info/top_level.txt
irisml_tasks_ultralytics-0.0.3.dist-info/RECORD
