Metadata-Version: 2.1
Name: irisml-tasks-ultralytics
Version: 0.0.3
Requires-Python: >=3.10
License-File: LICENSE
Requires-Dist: irisml
Requires-Dist: ultralytics-nogui <9
